{ "type": "FeatureCollection", "crs": { "type": "name", "properties": { "name": "urn:ogc:def:crs:OGC:1.3:CRS84" } }, "features": [
{ "type": "Feature", "properties": { "Name": "Thomas", "Description": "Tue Sep 24 19:35:32 EDT 2013; Location Accuracy: " }, "geometry": { "type": "Point", "coordinates": [ , , 0.0 ] } },
{ "type": "Feature", "properties": { "Name": "Thomas", "Description": "Tue Sep 24 19:34:05 EDT 2013; Location Accuracy: " }, "geometry": { "type": "Point", "coordinates": [ , , 0.0 ] } },
<<<<<<< HEAD
{ "type": "Feature", "properties": { "Name": "Thomas", "Description": "Tue Sep 24 19:33:12 EDT 2013; Location Accuracy: " }, "geometry": { "type": "Point", "coordinates": [ , , 0.0 ] } },
<<<<<<< HEAD
{ "type": "Feature", "properties": { "Name": "Thomas", "Description": "Tue Sep 24 19:25:52 EDT 2013; Location Accuracy: " }, "geometry": { "type": "Point", "coordinates": [ , , 0.0 ] } },
<<<<<<< HEAD
{ "type": "Feature", "properties": { "Name": "Thomas", "Description": "Tue Sep 24 19:23:11 EDT 2013; Location Accuracy: " }, "geometry": { "type": "Point", "coordinates": [ , , 0.0 ] } },
{ "type": "Feature", "properties": { "Name": "Thomas", "Description": "Tue Sep 24 19:19:09 EDT 2013; Location Accuracy: " }, "geometry": { "type": "Point", "coordinates": [ , , 0.0 ] } },
{ "type": "Feature", "properties": { "Name": "Thomas", "Description": "Tue Sep 24 19:18:29 EDT 2013; Location Accuracy: " }, "geometry": { "type": "Point", "coordinates": [ , , 0.0 ] } },
=======
>>>>>>> 366e6b7845624662ec837677ca7474b45c45e0ca
=======
>>>>>>> 3746b5478342eba8f920edc18dc174927a3dfd98
=======
>>>>>>> 24d39323882aa31c92389555ba546bd3b48a6ba6
{ "type": "Feature", "properties": { "Name": "Hila Gutfreund", "Description": "Tue Sep 24 18:51:39 EDT 2013; Location Accuracy: 65.000000" }, "geometry": { "type": "Point", "coordinates": [ -73.961160, 40.809296, 0.0 ] } },
{ "type": "Feature", "properties": { "Name": "William Falk-Wallace", "Description": " Mon Sep 23 12:50:28 EDT 2013; Location Accuracy: 65.000000" }, "geometry": { "type": "Point", "coordinates": [ -73.961323, 40.809402, 0.0 ] } },
{ "type": "Feature", "properties": { "Name": "William Falk-Wallace", "Description": "Thu Sep 19 09:16:33 EDT 2013; Location Accuracy: 65.000000" }, "geometry": { "type": "Point", "coordinates": [ -73.969655, 40.800827, 0.0 ] } }
]}
